structquery/__init__.py
structquery/main.py
structquery/prompts.py
structquery-2025.12.21164456.dist-info/METADATA
structquery-2025.12.21164456.dist-info/WHEEL
structquery-2025.12.21164456.dist-info/top_level.txt
structquery-2025.12.21164456.dist-info/RECORD
