Metadata-Version: 2.4
Name: structquery
Version: 2025.12.21164456
Summary: A new package that transforms unstructured text queries into highly structured, search-optimized outputs. The package takes a user's text input, such as a search query or a description of information
Author-email: structquery <hi@eugene.plus>
License: MIT
Project-URL: Homepage, https://github.com/chigwell/structquery
Requires-Python: >=3.9
Requires-Dist: langchain-llm7>=0.0.0
Requires-Dist: llmatch-messages>=0.0.0
Requires-Dist: langchain-core>=0.3.0
